pyTableMaker/__init__.py
pyTableMaker/gui.py
pyTableMaker/table.py
pyTableMaker/utils.py
pyTableMaker-2.0.1.dist-info/LICENSE
pyTableMaker-2.0.1.dist-info/METADATA
pyTableMaker-2.0.1.dist-info/WHEEL
pyTableMaker-2.0.1.dist-info/top_level.txt
pyTableMaker-2.0.1.dist-info/RECORD
